backwise/__init__.py
backwise/backtest.py
backwise/constants/__init__.py
backwise/exceptions/__init__.py
backwise/exchange.py
backwise/exchanges/__init__.py
backwise/exchanges/_boilerplate.py
backwise/exchanges/_ccxt.py
backwise/exchanges/binance.py
backwise/indicator.py
backwise/indicators/__init__.py
backwise/indicators/rsi.py
backwise/mixins/__init__.py
backwise/mixins/exchange.py
backwise/mixins/exchange_amount.py
backwise/mixins/exchange_currency.py
backwise/mixins/exchange_interface.py
backwise/mixins/exchange_market.py
backwise/mixins/exchange_ohlcv.py
backwise/mixins/exchange_ticker.py
backwise/mixins/exchange_timeframe.py
backwise/mixins/exchange_trade.py
backwise/strategy.py
backwise/tools/__init__.py
backwise/tools/floor_ceil_datetime.py
backwise/tools/get_chunk_range.py
backwise/tools/get_datetime.py
backwise/tools/get_timeframes.py
backwise/tools/is_timezone.py
backwise/tools/to_datetime.py
backwise/tools/to_decimal.py
backwise/tools/to_slug.py
backwise-0.1.0.dist-info/WHEEL
backwise-0.1.0.dist-info/METADATA
backwise-0.1.0.dist-info/RECORD
